rddlgym/__init__.py
rddlgym/env.py
rddlgym/runner.py
rddlgym/trajectory.py
rddlgym/utils.py
rddlgym/files/CarParking-v1.rddl
rddlgym/files/CrossingTraffic-1.rddl
rddlgym/files/CrossingTraffic-10.rddl
rddlgym/files/GameOfLife-1.rddl
rddlgym/files/GameOfLife-10.rddl
rddlgym/files/HVAC-3.rddl
rddlgym/files/HVAC-6.rddl
rddlgym/files/HVAC-v1.rddl
rddlgym/files/Mars_Rover.rddl
rddlgym/files/Navigation-v0.rddl
rddlgym/files/Navigation-v1.rddl
rddlgym/files/Navigation-v2.rddl
rddlgym/files/Navigation-v3.rddl
rddlgym/files/Reservoir-10.rddl
rddlgym/files/Reservoir-20.rddl
rddlgym/files/Reservoir-30.rddl
rddlgym/files/Reservoir-8.rddl
rddlgym/files/Sysadmin-1.rddl
rddlgym/files/Sysadmin-10.rddl
rddlgym/files/all.json
rddlgym-0.5.15.data/scripts/rddlgym
tests/__init__.py
tests/test_env.py
tests/test_runner.py
tests/test_trajectory.py
rddlgym-0.5.15.dist-info/LICENSE
rddlgym-0.5.15.dist-info/METADATA
rddlgym-0.5.15.dist-info/WHEEL
rddlgym-0.5.15.dist-info/top_level.txt
rddlgym-0.5.15.dist-info/RECORD
