Metadata-Version: 2.1
Name: rddlgym
Version: 0.5.15
Summary: rddlgym: A toolkit for working with RDDL domains in Python3.
Home-page: https://github.com/thiagopbueno/rddlgym
Author: Thiago P. Bueno
Author-email: thiago.pbueno@gmail.com
License: GNU General Public License v3.0
Keywords: rddl,toolkit
Platform: UNKNOWN
Classifier: Development Status :: 3 - Alpha
Classifier: Environment :: Console
Classifier: Intended Audience :: Science/Research
Classifier: License :: OSI Approved :: GNU General Public License v3 (GPLv3)
Classifier: Natural Language :: English
Classifier: Operating System :: OS Independent
Classifier: Programming Language :: Python :: 3
Classifier: Topic :: Scientific/Engineering :: Artificial Intelligence
Requires-Python: >=3.6
Requires-Dist: tensorflow (<2.0)
Requires-Dist: gym
Requires-Dist: pandas
Requires-Dist: matplotlib
Requires-Dist: pyrddl
Requires-Dist: rddl2tf
